smalig/__init__.py
smalig/__main__.py
smalig/grammar.yaml
smalig/cli/app.py
smalig/utils/__init__.py
smalig-0.1.10.dist-info/licenses/LICENSE
smalig-0.1.10.dist-info/METADATA
smalig-0.1.10.dist-info/WHEEL
smalig-0.1.10.dist-info/entry_points.txt
smalig-0.1.10.dist-info/top_level.txt
smalig-0.1.10.dist-info/RECORD
