Metadata-Version: 2.4
Name: smalig
Version: 0.1.10
Summary: Smali ByteCode info (grammar) fetch tool written in Python
Author-email: AbhiTheModder <allinoneallinone00@gmail.com>
License: MIT License
Project-URL: homepage, https://github.com/RevEngiSquad/smalig
Project-URL: source, https://github.com/RevEngiSquad/smalig
Project-URL: issues, https://github.com/RevEngiSquad/smalig/issues
Keywords: smali,grammar,parser,android,reverse-engineering
Classifier: Development Status :: 4 - Beta
Classifier: Natural Language :: English
Classifier: Intended Audience :: Developers
Classifier: License :: OSI Approved :: MIT License
Classifier: Programming Language :: Python :: 3
Classifier: Programming Language :: Python :: 3.10
Classifier: Programming Language :: Python :: 3.11
Classifier: Programming Language :: Python :: 3.12
Classifier: Topic :: Software Development :: Libraries :: Python Modules
Classifier: Topic :: Text Processing :: General
Classifier: Topic :: Utilities
Classifier: Operating System :: OS Independent
Requires-Python: >=3.10
License-File: LICENSE
Requires-Dist: PyYAML
Dynamic: license-file
